{
  "_class": "group",
  "do_objectID": "5E936EF2-D939-4307-9E50-C73417808EFF",
  "exportOptions": {
    "_class": "exportOptions",
    "exportFormats": [
    ],
    "includedLayerIds": [
    ],
    "layerOptions": 0,
    "shouldTrim": false
  },
  "frame": {
    "_class": "rect",
    "constrainProportions": false,
    "height": 29,
    "width": 335,
    "x": 20,
    "y": 489
  },
  "hasClickThrough": false,
  "isFlippedHorizontal": false,
  "isFlippedVertical": false,
  "isLocked": false,
  "isVisible": true,
  "layerListExpandedType": 0,
  "layers": [
    {
      "class": "group",
      "id": "6F08EA1A-F225-4C91-A15C-BA34A4A9E835"
    },
    {
      "class": "group",
      "id": "BB8B889E-B878-4508-8534-BB000ED9D55A"
    },
    {
      "class": "group",
      "id": "550E0382-1630-4CEE-9F56-0963B4F13562"
    }
  ],
  "name": "Navigation/Nav Bar/3 Tabs - First",
  "nameIsFixed": false,
  "resizingConstraint": 63,
  "resizingType": 0,
  "rotation": 0,
  "shouldBreakMaskChain": false,
  "style": {
    "_class": "style",
    "endDecorationType": 0,
    "miterLimit": 10,
    "startDecorationType": 0
  },
  "userInfo": {
    "com.animaapp.stc-sketch-plugin": {
      "kModelPropertiesKey": {
      }
    }
  }
}