{
  "_class": "group",
  "do_objectID": "5183E737-41DB-4963-A6A2-844969A21899",
  "exportOptions": {
    "_class": "exportOptions",
    "exportFormats": [
    ],
    "includedLayerIds": [
    ],
    "layerOptions": 0,
    "shouldTrim": false
  },
  "frame": {
    "_class": "rect",
    "constrainProportions": false,
    "height": 22,
    "width": 67,
    "x": 10,
    "y": 8
  },
  "hasClickThrough": false,
  "isFlippedHorizontal": false,
  "isFlippedVertical": false,
  "isLocked": false,
  "isVisible": true,
  "layerListExpandedType": 2,
  "layers": [
    {
      "class": "text",
      "id": "999FF8DB-2483-4541-82BB-5E8C021BF312"
    },
    {
      "class": "group",
      "id": "30F9C928-99F5-4F51-B7D1-B04883918BD7"
    }
  ],
  "name": "Group 2",
  "nameIsFixed": false,
  "resizingConstraint": 41,
  "resizingType": 1,
  "rotation": 0,
  "shouldBreakMaskChain": false,
  "style": {
    "_class": "style",
    "endDecorationType": 0,
    "miterLimit": 10,
    "startDecorationType": 0
  }
}