{
  "_class": "shapePath",
  "booleanOperation": 1,
  "do_objectID": "17FC2A65-92A8-46A7-AC0E-3B7FD01C3B41",
  "edited": true,
  "exportOptions": {
    "_class": "exportOptions",
    "exportFormats": [
    ],
    "includedLayerIds": [
    ],
    "layerOptions": 0,
    "shouldTrim": false
  },
  "frame": {
    "_class": "rect",
    "constrainProportions": false,
    "height": 21.6345,
    "width": 23,
    "x": 1,
    "y": 1
  },
  "isFlippedHorizontal": false,
  "isFlippedVertical": false,
  "isLocked": false,
  "isVisible": true,
  "layerListExpandedType": 0,
  "name": "Fill 3",
  "nameIsFixed": false,
  "path": {
    "_class": "path",
    "isClosed": false,
    "pointRadiusBehaviour": 1,
    "points": [
      {
        "_class": "curvePoint",
        "cornerRadius": 0,
        "curveFrom": "{0.87793478260869562, 0}",
        "curveMode": 4,
        "curveTo": "{0.76086956521739135, 0}",
        "hasCurveFrom": true,
        "hasCurveTo": false,
        "point": "{0.76086956521739135, 0}"
      },
      {
        "_class": "curvePoint",
        "cornerRadius": 0,
        "curveFrom": "{0.99786956521739134, 0.10836857796574915}",
        "curveMode": 3,
        "curveTo": "{0.96304347826086956, 0.073193279253044946}",
        "hasCurveFrom": true,
        "hasCurveTo": true,
        "point": "{0.99419565217391315, 0.10464766923201366}"
      },
      {
        "_class": "curvePoint",
        "cornerRadius": 0,
        "curveFrom": "{1, 0.11962374910443972}",
        "curveMode": 4,
        "curveTo": "{1, 0.11384594051168277}",
        "hasCurveFrom": false,
        "hasCurveTo": true,
        "point": "{1, 0.11962374910443972}"
      },
      {
        "_class": "curvePoint",
        "cornerRadius": 0,
        "curveFrom": "{0.92695652173913046, 0.91707689107675239}",
        "curveMode": 4,
        "curveTo": "{1, 0.97014028519263229}",
        "hasCurveFrom": true,
        "hasCurveTo": false,
        "point": "{1, 0.97014028519263229}"
      },
      {
        "_class": "curvePoint",
        "cornerRadius": 0,
        "curveFrom": "{0.59284782608695652, 0.85511567172802705}",
        "curveMode": 3,
        "curveTo": "{0.81973913043478253, 0.85511567172802705}",
        "hasCurveFrom": true,
        "hasCurveTo": true,
        "point": "{0.71739130434782605, 0.85511567172802705}"
      },
      {
        "_class": "curvePoint",
        "cornerRadius": 0,
        "curveFrom": "{0.47139130434782606, 0.94289213986919052}",
        "curveMode": 4,
        "curveTo": "{0.52858695652173904, 0.94289213986919052}",
        "hasCurveFrom": true,
        "hasCurveTo": true,
        "point": "{0.5, 1}"
      },
      {
        "_class": "curvePoint",
        "cornerRadius": 0,
        "curveFrom": "{0.18028260869565216, 0.85511567172802705}",
        "curveMode": 3,
        "curveTo": "{0.40715217391304348, 0.85511567172802705}",
        "hasCurveFrom": true,
        "hasCurveTo": true,
        "point": "{0.28260869565217389, 0.85511567172802705}"
      },
      {
        "_class": "curvePoint",
        "cornerRadius": 0,
        "curveFrom": "{0, 0.97014028519263229}",
        "curveMode": 4,
        "curveTo": "{0.073043478260869557, 0.91707689107675239}",
        "hasCurveFrom": false,
        "hasCurveTo": true,
        "point": "{0, 0.97014028519263229}"
      },
      {
        "_class": "curvePoint",
        "cornerRadius": 0,
        "curveFrom": "{0, 0.11384594051168277}",
        "curveMode": 4,
        "curveTo": "{0, 0.11962374910443972}",
        "hasCurveFrom": true,
        "hasCurveTo": false,
        "point": "{0, 0.11962374910443972}"
      },
      {
        "_class": "curvePoint",
        "cornerRadius": 0,
        "curveFrom": "{0.036956521739130339, 0.073193279253044946}",
        "curveMode": 3,
        "curveTo": "{0.0021304347826086732, 0.10836857796574915}",
        "hasCurveFrom": true,
        "hasCurveTo": true,
        "point": "{0.0058043478260868678, 0.10464766923201366}"
      },
      {
        "_class": "curvePoint",
        "cornerRadius": 0,
        "curveFrom": "{0.3863695652173913, 0}",
        "curveMode": 3,
        "curveTo": "{0.12206521739130431, 0}",
        "hasCurveFrom": true,
        "hasCurveTo": true,
        "point": "{0.2391304347826087, 0}"
      },
      {
        "_class": "curvePoint",
        "cornerRadius": 0,
        "curveFrom": "{0.46382608695652172, 0.11807529640158085}",
        "curveMode": 4,
        "curveTo": "{0.46084782608695646, 0.11345304952737524}",
        "hasCurveFrom": false,
        "hasCurveTo": true,
        "point": "{0.46382608695652172, 0.11807529640158085}"
      },
      {
        "_class": "curvePoint",
        "cornerRadius": 0,
        "curveFrom": "{0.49971739130434789, 0.17490582171993801}",
        "curveMode": 1,
        "curveTo": "{0.49971739130434789, 0.17490582171993801}",
        "hasCurveFrom": false,
        "hasCurveTo": false,
        "point": "{0.49971739130434789, 0.17490582171993801}"
      },
      {
        "_class": "curvePoint",
        "cornerRadius": 0,
        "curveFrom": "{0.53915217391304349, 0.11345304952737524}",
        "curveMode": 4,
        "curveTo": "{0.53604347826086962, 0.11828329751092011}",
        "hasCurveFrom": true,
        "hasCurveTo": false,
        "point": "{0.53604347826086962, 0.11828329751092011}"
      },
      {
        "_class": "curvePoint",
        "cornerRadius": 0,
        "curveFrom": "{0.76086956521739135, 0}",
        "curveMode": 4,
        "curveTo": "{0.61363043478260859, 0}",
        "hasCurveFrom": false,
        "hasCurveTo": true,
        "point": "{0.76086956521739135, 0}"
      }
    ]
  },
  "resizingConstraint": 63,
  "resizingType": 0,
  "rotation": 0,
  "shouldBreakMaskChain": false
}